{"cameraMode":{"drawMode":0,"name":"Shaded","section":"Shading Mode"},"sceneLighting":true,"audioPlay":false,"sceneViewState":{"showFog":true,"showMaterialUpdate":false,"showSkybox":true,"showFlares":true,"showImageEffects":true,"showParticleSystems":true},"in2DMode":false,"pivot":{"x":-1.1041059494018555,"y":-2.6209020614624025,"z":16.39675521850586},"rotation":{"x":0.12409128248691559,"y":-0.037201300263404849,"z":0.004655685741454363,"w":0.991563081741333},"size":35.88330078125,"orthographic":false}